.dir-locals.el
CHANGES.rst
MANIFEST.in
Makefile
Makefile.release
Makefile.virtualenv
README.rst
requirements-test.txt
requirements.txt
setup.cfg
setup.py
version.txt
doc/Makefile
doc/conf.py
doc/connection.rst
doc/dialect.rst
doc/funcs.rst
doc/index.rst
doc/proxy.rst
doc/types.rst
src/metapensiero.sqlalchemy.asyncpg.egg-info/PKG-INFO
src/metapensiero.sqlalchemy.asyncpg.egg-info/SOURCES.txt
src/metapensiero.sqlalchemy.asyncpg.egg-info/dependency_links.txt
src/metapensiero.sqlalchemy.asyncpg.egg-info/namespace_packages.txt
src/metapensiero.sqlalchemy.asyncpg.egg-info/requires.txt
src/metapensiero.sqlalchemy.asyncpg.egg-info/top_level.txt
src/metapensiero/sqlalchemy/asyncpg/__init__.py
src/metapensiero/sqlalchemy/asyncpg/connection.py
src/metapensiero/sqlalchemy/asyncpg/dialect.py
src/metapensiero/sqlalchemy/asyncpg/funcs.py
src/metapensiero/sqlalchemy/asyncpg/proxy.py
src/metapensiero/sqlalchemy/asyncpg/types.py
tests/conftest.py
tests/test_compile.py
tests/test_connection.py
tests/test_proxy.py
tests/test_select.py
tests/test_types.py