Metadata-Version: 1.1
Name: metapensiero.sqlalchemy.asyncpg
Version: 0.1
Summary: SQLAlchemy adaptor for asyncpg
Home-page: https://gitlab.com/metapensiero/metapensiero.sqlalchemy.asyncpg.git
Author: Lele Gaifax
Author-email: lele@metapensiero.it
License: GPLv3+
Platform: UNKNOWN
Classifier: Development Status :: 3 - Alpha
Classifier: Programming Language :: Python
Classifier: Programming Language :: Python :: 3
Classifier: Programming Language :: Python :: 3.5
Classifier: Programming Language :: Python :: 3.6
